{"matches": [{"date": "2015-10-10T22:10:56.683+01:00", "outcome": "loss", "opp": "incognito", "tournament": "hacks$"}, {"date": "2015-10-10T22:10:56.827+01:00", "outcome": "win", "opp": "nathan", "tournament": "hacks$"}, {"date": "2015-10-10T22:10:56.869+01:00", "outcome": "win", "opp": "ohmu", "tournament": "hacks$"}, {"date": "2015-10-10T22:10:56.900+01:00", "outcome": "win", "opp": "calvin", "tournament": "hacks$"}, {"date": "2015-10-10T22:10:56.926+01:00", "outcome": "loss", "opp": "cera", "tournament": "hacks$"}, {"date": "2015-09-14T00:42:23.750+01:00", "outcome": "loss", "opp": "chuck lee", "tournament": "bw2"}, {"date": "2015-09-14T00:42:23.864+01:00", "outcome": "win", "opp": "jive", "tournament": "bw2"}, {"date": "2015-09-14T00:42:23.913+01:00", "outcome": "win", "opp": "licus", "tournament": "bw2"}, {"date": "2015-09-14T00:42:23.951+01:00", "outcome": "win", "opp": "nickpeaches", "tournament": "bw2"}, {"date": "2015-09-14T00:42:23.969+01:00", "outcome": "loss", "opp": "c .rabbit", "tournament": "bw2"}, {"date": "2015-10-04T18:38:20.541-05:00", "outcome": "loss", "opp": "mattomega", "tournament": "hacks$"}, {"date": "2015-10-04T18:38:20.805-05:00", "outcome": "loss", "opp": "spookyman", "tournament": "hacks$"}], "user_id": "henrius", "matchesPlayed": 12, "winloss": "6/6"}